README.txt
setup.py
./tk0/__init__.py
./tk0/gaerunner.py
tk0.gaerunner.egg-info/PKG-INFO
tk0.gaerunner.egg-info/SOURCES.txt
tk0.gaerunner.egg-info/dependency_links.txt
tk0.gaerunner.egg-info/entry_points.txt
tk0.gaerunner.egg-info/requires.txt
tk0.gaerunner.egg-info/top_level.txt