Metadata-Version: 1.0
Name: tk0.gaerunner
Version: 0.1.1
Summary: Python script launcher for Google App Engine (using remote API call)
Home-page: UNKNOWN
Author: Takeshi Komiya
Author-email: i.tkomiya at gmail.com
License: ASL
Keywords: google,app,engine,appengine,gae
Platform: UNKNOWN
Classifier: Development Status :: 3 - Alpha
Classifier: Environment :: Console
Classifier: Intended Audience :: Developers
Classifier: License :: OSI Approved :: Apache Software License
Classifier: Programming Language :: Python
Classifier: Topic :: Software Development
